README.rst
pyproject.toml
setup.py
bin/op
libop.egg-info/PKG-INFO
libop.egg-info/SOURCES.txt
libop.egg-info/dependency_links.txt
libop.egg-info/top_level.txt
libop.egg-info/zip-safe
op/__init__.py
op/brokers.py
op/handler.py
op/logging.py
op/message.py
op/objects.py
op/runtime.py
op/storage.py
op/threads.py
op/utility.py
op/modules/__init__.py
op/modules/cmd.py
op/modules/err.py
op/modules/irc.py
op/modules/log.py
op/modules/mod.py
op/modules/rss.py
op/modules/tdo.py
op/modules/thr.py
op/modules/tmr.py