Metadata-Version: 2.1
Name: libop
Version: 32
Summary: original programmer
Author-email: Bart Thate <bthate@dds.nl>
License: Public Domain
Project-URL: home, https://pypi.org/project/libop
Project-URL: bugs, https://github.com/xobjectz/libop/issues
Project-URL: source, https://github.com/xobjectz/libop
Classifier: Development Status :: 3 - Alpha
Classifier: License :: Public Domain
Classifier: Operating System :: Unix
Classifier: Programming Language :: Python
Classifier: Topic :: Utilities
